ffmpeg_quality_metrics/__init__.py
ffmpeg_quality_metrics/__main__.py
ffmpeg_quality_metrics/ffmpeg_quality_metrics.py
ffmpeg_quality_metrics/gui.py
ffmpeg_quality_metrics/gui_main.py
ffmpeg_quality_metrics/log.py
ffmpeg_quality_metrics/py.typed
ffmpeg_quality_metrics/utils.py
ffmpeg_quality_metrics/vmaf_models/LICENSE
ffmpeg_quality_metrics/vmaf_models/vmaf_4k_v0.6.1.json
ffmpeg_quality_metrics/vmaf_models/vmaf_v0.6.1.json
ffmpeg_quality_metrics/vmaf_models/vmaf_v0.6.1neg.json
ffmpeg_quality_metrics-3.11.2.dist-info/WHEEL
ffmpeg_quality_metrics-3.11.2.dist-info/entry_points.txt
ffmpeg_quality_metrics-3.11.2.dist-info/METADATA
ffmpeg_quality_metrics-3.11.2.dist-info/RECORD
