Metadata-Version: 2.4
Name: ffmpeg-quality-metrics
Version: 3.11.2
Summary: Calculate video quality metrics with FFmpeg (SSIM, PSNR, VMAF)
Author: Werner Robitza
Author-email: Werner Robitza <werner.robitza@gmail.com>
License-Expression: MIT
Classifier: Development Status :: 4 - Beta
Classifier: Intended Audience :: Developers
Classifier: Topic :: Multimedia :: Video
Classifier: Programming Language :: Python :: 3
Classifier: Programming Language :: Python :: 3.10
Classifier: Programming Language :: Python :: 3.11
Classifier: Programming Language :: Python :: 3.12
Classifier: Programming Language :: Python :: 3.13
Classifier: Programming Language :: Python :: 3.14
Requires-Dist: tqdm
Requires-Dist: ffmpeg-progress-yield>=1.0.1
Requires-Dist: plotly>=5.0.0 ; extra == 'gui'
Requires-Dist: dash>=3.2.0 ; extra == 'gui'
Requires-Python: >=3.10
Project-URL: Homepage, https://github.com/slhck/ffmpeg-quality-metrics
Project-URL: Repository, https://github.com/slhck/ffmpeg-quality-metrics
Provides-Extra: gui
